robustipy/__init__.py
robustipy/bootstrap_utils.py
robustipy/figures.py
robustipy/models.py
robustipy/prototypes.py
robustipy/requirements.txt
robustipy/utils.py
robustipy-1.0.0.dist-info/METADATA
robustipy-1.0.0.dist-info/WHEEL
robustipy-1.0.0.dist-info/licenses/LICENSE
robustipy-1.0.0.dist-info/RECORD
