Metadata-Version: 2.4
Name: robustipy
Version: 1.0.0
Summary: Multiversal estimation for robust inference.
Project-URL: Homepage, https://robustipy.github.io/
Project-URL: Repository, https://github.com/RobustiPy/robustipy
Project-URL: Issues, https://github.com/RobustiPy/robustipy/issues
Author-email: Daniel Valdenegro <daniel.valdenegro@demography.ox.ac.uk>, Jiani Yan <jiani.yan@sociology.ox.ac.uk>, Duiyi Dai <duiyi.dai@demography.ox.ac.uk>, Charles Rahal <charles.rahal@demography.ox.ac.uk>
Maintainer-email: Daniel Valdenegro <daniel.valdenegro@demography.ox.ac.uk>, Charles Rahal <charles.rahal@demography.ox.ac.uk>
License: GPLv3
License-File: LICENSE
Classifier: Development Status :: 5 - Production/Stable
Classifier: License :: OSI Approved :: GNU General Public License v3 (GPLv3)
Classifier: Topic :: Scientific/Engineering
Requires-Python: >=3.11
Requires-Dist: inquirer==3.4.0
Requires-Dist: joblib>=1.2.0
Requires-Dist: joypy>=0.2.6
Requires-Dist: linearmodels>=4.27
Requires-Dist: matplotlib>=3.6.1
Requires-Dist: numpy>=1.23.2
Requires-Dist: pandas>=1.4.3
Requires-Dist: rich>=13.6.0
Requires-Dist: scikit-learn>=1.5.0
Requires-Dist: scipy>=1.9.0
Requires-Dist: seaborn>=0.13.2
Requires-Dist: shap>=0.46.0
Requires-Dist: statsmodels>=0.13.2
